bymanim/__init__.py
bymanim/_version.py
bymanim/components/__init__.py
bymanim/components/text/__init__.py
bymanim/components/text/paragraph.py
bymanim/slides/__init__.py
bymanim/slides/manim_slide.py
bymanim-0.0.1.dist-info/LICENSE.md
bymanim-0.0.1.dist-info/METADATA
bymanim-0.0.1.dist-info/WHEEL
bymanim-0.0.1.dist-info/top_level.txt
bymanim-0.0.1.dist-info/RECORD
