Metadata-Version: 2.1
Name: bymanim
Version: 0.0.1
Summary: A Manim Packages with an easier and clean user interface.
Author: @b64-Lorenzo (Lorenzo Zambelli)
Author-email: Lorenzo Zambelli <bytemath@lorenzozambelli.it>
Project-URL: Homepage, https://gitlab.com/ByteMath/python/bymanim
Project-URL: documentation, https://bytemath.gitlab.io/python/ByMaNiM/index.html
Project-URL: source, https://gitlab.com/ByteMath/python/ByMaNiM
Project-URL: download, https://pypi.org/project/byma/#files
Project-URL: tracker, https://gitlab.com/ByteMath/python/ByMaNiM/-/issues
Keywords: python,manim,manim_slides
Classifier: Programming Language :: Python :: 3
Classifier: License :: OSI Approved :: BSD License
Classifier: Topic :: Scientific/Engineering
Classifier: Operating System :: OS Independent
Requires-Python: >=3.7
License-File: LICENSE.md
